requirements.txt
setup.cfg
setup.py
test-requirements.txt
./LICENSE.md
./README.md
Treadmill.egg-info/PKG-INFO
Treadmill.egg-info/SOURCES.txt
Treadmill.egg-info/dependency_links.txt
Treadmill.egg-info/entry_points.txt
Treadmill.egg-info/not-zip-safe
Treadmill.egg-info/requires.txt
Treadmill.egg-info/top_level.txt
deploy/__init__.py
deploy/ansible.cfg
deploy/aws.yml
deploy/cell.yml
deploy/controller.inventory
deploy/destroy-cell.yml
deploy/freeipa.yml
deploy/instance.yml
deploy/master.yml
deploy/node.yml
deploy/vpc.yml
deploy/library/__init__.py
deploy/library/ec2_vpc_net_custom.py
deploy/roles/base-setup/tasks/main.yml
deploy/roles/destroy-cell/meta/main.yml
deploy/roles/destroy-cell/tasks/igw.yml
deploy/roles/destroy-cell/tasks/instances.yml
deploy/roles/destroy-cell/tasks/main.yml
deploy/roles/destroy-cell/tasks/route-table.yml
deploy/roles/destroy-cell/tasks/security-group.yml
deploy/roles/destroy-cell/tasks/subnet.yml
deploy/roles/destroy-cell/tasks/vpc.yml
deploy/roles/dynamic-inventory/tasks/main.yml
deploy/roles/fetch-facts/tasks/ec2.yml
deploy/roles/fetch-facts/tasks/main.yml
deploy/roles/fetch-facts/tasks/route_table.yml
deploy/roles/fetch-facts/tasks/subnet.yml
deploy/roles/fetch-facts/tasks/vpc.yml
deploy/roles/instance/meta/main.yml
deploy/roles/instance/tasks/create-instance.yml
deploy/roles/instance/tasks/create-security-group.yml
deploy/roles/instance/tasks/get-controller-ip.yml
deploy/roles/instance/tasks/main.yml
deploy/roles/master/meta/main.yml
deploy/roles/master/tasks/main.yml
deploy/roles/master/tasks/scheduler.yml
deploy/roles/master/tasks/zookeeper.yml
deploy/roles/master/templates/myid
deploy/roles/master/templates/zoo.cfg
deploy/roles/node-server/defaults/main.yml
deploy/roles/node-server/meta/main.yml
deploy/roles/node-server/tasks/main.yml
deploy/roles/node-server/tasks/packages.yml
deploy/roles/node-server/tasks/treadmill_deps.yml
deploy/roles/node-server/tasks/treadmill_services.yml
deploy/roles/treadmill-base-setup/defaults/main.yml
deploy/roles/treadmill-base-setup/meta/main.yml
deploy/roles/treadmill-base-setup/tasks/main.yml
deploy/roles/treadmill-base-setup/tasks/packages.yml
deploy/roles/treadmill-base-setup/tasks/treadmill_base.yml
