Metadata-Version: 1.0
Name: Treadmill
Version: 0.0.2
Summary: UNKNOWN
Home-page: http://treadmill.github.io
Author: Morgan Stanley
Author-email: treadmill-oss@morganstanley.com
License: UNKNOWN
Platform: UNKNOWN
